<?xml version="1.0" encoding="utf-8" standalone="yes"?>
<d2LogicalModel xmlns="http://datex2.eu/schema/1_0/1_0" modelBaseVersion="1.0">
  <exchange>
    <supplierIdentification>
      <country>gb</country>
      <nationalIdentifier>NTCC</nationalIdentifier>
    </supplierIdentification>
  </exchange>
  <payloadPublication xmlns:xsi="http://www.w3.org/2001/XMLSchema-instance"
  xsi:type="SituationPublication" lang="en">
    <publicationTime>2013-04-25T02:01:19+01:00</publicationTime>
    <publicationCreator>
      <country>gb</country>
      <nationalIdentifier>NTCC</nationalIdentifier>
    </publicationCreator>
    <situation id="GUID578234404">
      <headerInformation>
        <areaOfInterest>national</areaOfInterest>
        <confidentiality>restrictedToAuthoritiesTrafficOperatorsAndPublishers</confidentiality>
        <informationUsage>broadcast</informationUsage>
        <informationStatus>real</informationStatus>
      </headerInformation>
      <situationRecord xsi:type="AbnormalTraffic" id="GUID1-578234405">
        <situationRecordCreationReference>U-13-0425-0002</situationRecordCreationReference>
        <situationRecordCreationTime>2013-04-25T01:33:23+01:00</situationRecordCreationTime>
        <situationRecordVersion>2</situationRecordVersion>
        <situationRecordVersionTime>2013-04-25T01:34:35+01:00</situationRecordVersionTime>
        <situationRecordFirstSupplierVersionTime>
        2013-04-25T01:34:35+01:00</situationRecordFirstSupplierVersionTime>
        <probabilityOfOccurrence>certain</probabilityOfOccurrence>
        <sourceInformation>
          <sourceCountry>gb</sourceCountry>
          <sourceName>
            <value lang="en">TCC System</value>
          </sourceName>
        </sourceInformation>
        <validity>
          <validityStatus>definedByValidityTimeSpec</validityStatus>
          <validityTimeSpecification>
            <overallStartTime>2013-04-25T01:33:37+01:00</overallStartTime>
            <overallEndTime>2013-04-25T02:45:00+01:00</overallEndTime>
            <validPeriod>
              <startOfPeriod>2013-04-25T01:33:37+01:00</startOfPeriod>
              <endOfPeriod>2013-04-25T02:45:00+01:00</endOfPeriod>
            </validPeriod>
          </validityTimeSpecification>
        </validity>
        <impact>
          <impactOnTraffic>heavy</impactOnTraffic>
          <impactDetails>
            <capacityRemaining>100.0</capacityRemaining>
            <numberOfLanesRestricted>2</numberOfLanesRestricted>
            <numberOfOperationalLanes>2</numberOfOperationalLanes>
            <originalNumberOfLanes>2</originalNumberOfLanes>
            <trafficRestrictionType>carriagewayPartiallyObstructed</trafficRestrictionType>
          </impactDetails>
          <delays>
            <delayTimeValue>600.0</delayTimeValue>
          </delays>
        </impact>
        <nonGeneralPublicComment>
          <comment>
            <value lang="en">On the A38 from Bodmin towards Exeter between the junctions with the
            A374 Plymouth and the A384, there are currently delays of 10 mins due to heavy traffic .
            Normal traffic conditions expected from 2:45 am. Link to Multimap: Unavailable Link to
            Streetmap: http://streetmap.co.uk/grid/270886,59580 Link to Disclaimer:
            http://www.highways.gov.uk/aboutus/2301.aspx</value>
          </comment>
        </nonGeneralPublicComment>
        <groupOfLocations>
          <locationContainedInGroup xsi:type="Point">
            <tpegpointLocation xsi:type="TPEGFramedPoint">
              <tpegDirection>eastBound</tpegDirection>
              <tpegLocationType>framedPoint</tpegLocationType>
              <framedPoint>
                <pointCoordinates>
                  <latitude>50.421833</latitude>
                  <longitude>-3.818914</longitude>
                </pointCoordinates>
                <name>
                  <descriptor>
                    <value lang="en">A38 eastbound between B3372 and A385</value>
                  </descriptor>
                  <tpegDescriptorType>linkName</tpegDescriptorType>
                </name>
              </framedPoint>
              <to xsi:type="TPEGJunction">
                <pointCoordinates>
                  <latitude>50.48619</latitude>
                  <longitude>-3.769238</longitude>
                </pointCoordinates>
                <name>
                  <descriptor>
                    <value lang="en">unknown</value>
                  </descriptor>
                  <tpegDescriptorType>junctionName</tpegDescriptorType>
                </name>
                <ilc>
                  <descriptor>
                    <value lang="en">A38</value>
                  </descriptor>
                  <tpegDescriptorType>tpegILCName1</tpegDescriptorType>
                </ilc>
                <ilc>
                  <descriptor>
                    <value lang="en">A384</value>
                  </descriptor>
                  <tpegDescriptorType>tpegILCName2</tpegDescriptorType>
                </ilc>
              </to>
              <from xsi:type="TPEGJunction">
                <pointCoordinates>
                  <latitude>50.38635</latitude>
                  <longitude>-4.080807</longitude>
                </pointCoordinates>
                <name>
                  <descriptor>
                    <value lang="en">unknown</value>
                  </descriptor>
                  <tpegDescriptorType>junctionName</tpegDescriptorType>
                </name>
                <ilc>
                  <descriptor>
                    <value lang="en">A38</value>
                  </descriptor>
                  <tpegDescriptorType>tpegILCName1</tpegDescriptorType>
                </ilc>
                <ilc>
                  <descriptor>
                    <value lang="en">A374</value>
                  </descriptor>
                  <tpegDescriptorType>tpegILCName2</tpegDescriptorType>
                </ilc>
              </from>
            </tpegpointLocation>
          </locationContainedInGroup>
        </groupOfLocations>
        <abnormalTrafficType>slowTraffic</abnormalTrafficType>
      </situationRecord>
    </situation>
  </payloadPublication>
</d2LogicalModel>
